{
  "project_info": {
    "project_number": "498714658181",
    "project_id": "tourismappv2",
    "storage_bucket": "tourismappv2.appspot.com"
  },
  "client": [
    {
      "client_info": {
        "mobilesdk_app_id": "1:498714658181:android:cba3a58b5c81b079f4f0ec",
        "android_client_info": {
          "package_name": "io.ionic.tourismapp"
        }
      },
      "oauth_client": [
        {
          "client_id": "498714658181-hm7iuo790nejcjpsh7t3ckds1mumnoma.apps.googleusercontent.com",
          "client_type": 3
        }
      ],
      "api_key": [
        {
          "current_key": "AIzaSyBz5qehFrIvZ9yLp9tRN6f5fsEzWJc-yRA"
        }
      ],
      "services": {
        "appinvite_service": {
          "other_platform_oauth_client": [
            {
              "client_id": "498714658181-hm7iuo790nejcjpsh7t3ckds1mumnoma.apps.googleusercontent.com",
              "client_type": 3
            }
          ]
        }
      }
    },
    {
      "client_info": {
        "mobilesdk_app_id": "1:498714658181:android:5c82d057d1ca06a1f4f0ec",
        "android_client_info": {
          "package_name": "io.ionic.tourismappv2"
        }
      },
      "oauth_client": [
        {
          "client_id": "498714658181-7483cudae2vagag0omuju5rqnsk8g2ur.apps.googleusercontent.com",
          "client_type": 1,
          "android_info": {
            "package_name": "io.ionic.tourismappv2",
            "certificate_hash": "3ab611584569aba926ba352da119ff907ebd9d0a"
          }
        },
        {
          "client_id": "498714658181-hm7iuo790nejcjpsh7t3ckds1mumnoma.apps.googleusercontent.com",
          "client_type": 3
        }
      ],
      "api_key": [
        {
          "current_key": "AIzaSyBz5qehFrIvZ9yLp9tRN6f5fsEzWJc-yRA"
        }
      ],
      "services": {
        "appinvite_service": {
          "other_platform_oauth_client": [
            {
              "client_id": "498714658181-hm7iuo790nejcjpsh7t3ckds1mumnoma.apps.googleusercontent.com",
              "client_type": 3
            }
          ]
        }
      }
    }
  ],
  "configuration_version": "1"
}